marleu_emr/__init__.py
marleu_emr/emr.py
marleu_emr-0.1.3.dist-info/entry_points.txt
marleu_emr-0.1.3.dist-info/WHEEL
marleu_emr-0.1.3.dist-info/METADATA
marleu_emr-0.1.3.dist-info/RECORD
