Metadata-Version: 2.1
Name: marleu-emr
Version: 0.1.3
Summary: Deployment tool for EMR
Home-page: https://github.com/mleuthold/python-tooling
License: MIT
Author: Martin Leuthold
Requires-Python: >=3.7,<4.0
Classifier: License :: OSI Approved :: MIT License
Classifier: Programming Language :: Python :: 3
Classifier: Programming Language :: Python :: 3.7
Classifier: Programming Language :: Python :: 3.8
Classifier: Programming Language :: Python :: 3.9
Requires-Dist: credstash (>=1.17,<2.0)
Requires-Dist: cryptography (==3.3.2)
Requires-Dist: paramiko (>=2.7,<3.0)
Requires-Dist: requests (>=2.25,<3.0)
Project-URL: Repository, https://github.com/mleuthold/python-tooling
